{
    "issue": [
{
    "number": "1",
    "title": "Just Want to Get and Get Got",
    "season": "Fall, 2022",
    "author": "Jack Corso",
    "text": "Lorem ipsum dolor sit amet, consectetur adipiscing elit, sed do eiusmod tempor incididunt ut labore et dolore magna aliqua. Nisl suscipit adipiscing bibendum est ultricies integer quis. Suscipit adipiscing bibendum est ultricies integer quis. Cras ornare arcu dui vivamus arcu. Ut placerat orci nulla pellentesque. Enim facilisis gravida neque convallis a cras semper auctor neque. Erat velit scelerisque in dictum non consectetur a erat. Integer eget aliquet nibh praesent tristique magna sit. Diam quis enim lobortis scelerisque fermentum. Et leo duis ut diam quam nulla porttitor massa id. Pellentesque nec nam aliquam sem et tortor consequat id porta. Senectus et netus et malesuada fames ac turpis. Venenatis urna cursus eget nunc. Pellentesque id nibh tortor id aliquet. Aliquam ultrices sagittis orci a. Orci ac auctor augue mauris augue neque gravida in. Egestas congue quisque egestas diam in arcu cursus euismod. Integer feugiat scelerisque varius morbi enim nunc faucibus a. Sed egestas egestas fringilla phasellus faucibus scelerisque eleifend donec. Maecenas volutpat blandit aliquam etiam erat velit scelerisque in dictum.
    Consectetur adipiscing elit ut aliquam purus sit amet. Nisl suscipit adipiscing bibendum est ultricies integer quis. Ut morbi tincidunt augue interdum velit euismod in. At quis risus sed vulputate odio ut. Etiam non quam lacus suspendisse faucibus interdum posuere. Metus vulputate eu scelerisque felis imperdiet proin fermentum. Sed nisi lacus sed viverra. Ultrices neque ornare aenean euismod. Sollicitudin ac orci phasellus egestas tellus rutrum tellus. Vel quam elementum pulvinar etiam non. Euismod nisi porta lorem mollis aliquam. Sit amet mauris commodo quis imperdiet massa. Magna fermentum iaculis eu non. Ultrices gravida dictum fusce ut placerat orci. Neque ornare aenean euismod elementum nisi quis. Consequat nisl vel pretium lectus quam id leo in. Sed viverra tellus in hac habitasse. Donec ultrices tincidunt arcu non sodales neque sodales ut etiam. Dolor sit amet consectetur adipiscing elit duis tristique. Erat velit scelerisque in dictum non consectetur a erat nam.
    Pellentesque eu tincidunt tortor aliquam nulla facilisi cras fermentum. Vitae nunc sed velit dignissim. Amet mattis vulputate enim nulla aliquet. Orci dapibus ultrices in iaculis nunc sed augue lacus. Enim nulla aliquet porttitor lacus luctus. Dictum non consectetur a erat nam at. Tincidunt arcu non sodales neque sodales. Velit egestas dui id ornare arcu odio. Aenean vel elit scelerisque mauris pellentesque pulvinar pellentesque habitant. Neque gravida in fermentum et sollicitudin ac orci phasellus egestas. Cras pulvinar mattis nunc sed blandit libero volutpat sed. Et magnis dis parturient montes nascetur ridiculus mus. Turpis cursus in hac habitasse platea dictumst quisque sagittis. Neque egestas congue quisque egestas diam in arcu. Nibh praesent tristique magna sit. Accumsan sit amet nulla facilisi morbi. Tincidunt tortor aliquam nulla facilisi cras fermentum odio. Ornare massa eget egestas purus. Vulputate dignissim suspendisse in est ante in nibh mauris cursus. Condimentum id venenatis a condimentum.
    Diam maecenas sed enim ut sem. Nisi quis eleifend quam adipiscing vitae proin sagittis nisl. Nisi vitae suscipit tellus mauris a diam maecenas sed enim. In pellentesque massa placerat duis ultricies lacus. Arcu felis bibendum ut tristique et egestas quis ipsum. Vitae auctor eu augue ut lectus arcu bibendum at varius. Pellentesque habitant morbi tristique senectus. Pretium fusce id velit ut tortor. Non pulvinar neque laoreet suspendisse. Eu consequat ac felis donec. Arcu vitae elementum curabitur vitae nunc sed velit dignissim. Rutrum tellus pellentesque eu tincidunt tortor aliquam nulla. Lectus magna fringilla urna porttitor rhoncus. In nibh mauris cursus mattis molestie a iaculis at erat. Nisl nisi scelerisque eu ultrices vitae. Sit amet consectetur adipiscing elit.
    Orci dapibus ultrices in iaculis nunc sed augue lacus viverra. Eu non diam phasellus vestibulum lorem. Placerat in egestas erat imperdiet sed euismod. Amet aliquam id diam maecenas ultricies mi eget. Tellus in hac habitasse platea dictumst vestibulum. Amet justo donec enim diam vulputate ut. Ut pharetra sit amet aliquam id. Quam id leo in vitae turpis massa. Amet consectetur adipiscing elit pellentesque habitant morbi tristique senectus et. Integer vitae justo eget magna fermentum. Adipiscing commodo elit at imperdiet dui accumsan sit amet nulla. Orci ac auctor augue mauris augue neque. Quam quisque id diam vel quam elementum pulvinar. Malesuada nunc vel risus commodo viverra maecenas accumsan. Et pharetra pharetra massa massa ultricies. Eget sit amet tellus cras adipiscing enim. Condimentum lacinia quis vel eros. Leo duis ut diam quam nulla porttitor massa."
}
    ]
}